{"skeleton":{"hash":"JGLfqNGFggU","spine":"4.1.21","x":-59.03,"y":-20.08,"width":119.05,"height":156.03,"images":"./images/","audio":"C:/Users/ziya.rahimov/Desktop/Code games/Survivor io/Construction worker zombie"},"bones":[{"name":"root"},{"name":"bone","parent":"root","x":-0.09,"y":12.48},{"name":"body","parent":"bone","length":38.78,"rotation":89.59,"x":-0.28,"y":1.01},{"name":"head","parent":"body","length":68.93,"rotation":-0.75,"x":38.78},{"name":"left_hand","parent":"body","length":27.58,"rotation":-82.03,"x":29.97,"y":22.26},{"name":"right_hand","parent":"body","length":29.62,"rotation":-92.83,"x":27.19,"y":-17.38},{"name":"right_leg","parent":"bone","length":28.07,"rotation":-79.4,"x":11.9,"y":15.71},{"name":"left_leg","parent":"bone","length":28.27,"rotation":-95.78,"x":-13.91,"y":16.06},{"name":"shadow","parent":"bone","length":9.8,"rotation":-90,"x":-0.08,"y":-5.19}],"slots":[{"name":"Layer_15","bone":"root","attachment":"Layer_15"},{"name":"shadow","bone":"shadow","attachment":"shadow"},{"name":"right_leg","bone":"right_leg","attachment":"right_leg"},{"name":"left_leg","bone":"left_leg","attachment":"left_leg"},{"name":"head","bone":"head","attachment":"head"},{"name":"right_hand","bone":"right_hand","attachment":"right_hand"},{"name":"body","bone":"body","attachment":"body"},{"name":"left_hand","bone":"left_hand","attachment":"left_hand"},{"name":"shadow_white","bone":"shadow","attachment":"shadow_white"},{"name":"right_leg_white","bone":"right_leg","attachment":"right_leg_white"},{"name":"left_leg_white","bone":"left_leg","attachment":"left_leg_white"},{"name":"head_white","bone":"head","attachment":"head_white"},{"name":"right_hand_white","bone":"right_hand","attachment":"right_hand_white"},{"name":"body_white","bone":"body","attachment":"body_white"},{"name":"left_hand_right","bone":"left_hand","attachment":"left_hand_right"}],"skins":[{"name":"default","attachments":{"body":{"body":{"x":18.69,"y":0.44,"rotation":-89.59,"width":89,"height":54}},"body_white":{"body_white":{"x":18.69,"y":0.44,"rotation":-89.59,"width":89,"height":54}},"head":{"head":{"x":20.71,"y":-0.82,"rotation":-88.84,"width":91,"height":126}},"head_white":{"head_white":{"x":20.71,"y":-0.82,"rotation":-88.84,"width":91,"height":126}},"Layer_15":{"Layer_15":{"x":0.5,"y":0.5,"rotation":-0.07,"width":119,"height":41}},"left_hand":{"left_hand":{"x":13.97,"rotation":-7.56,"width":36,"height":21}},"left_hand_right":{"left_hand_right":{"x":13.97,"rotation":-7.56,"width":36,"height":21}},"left_leg":{"left_leg":{"x":13.52,"y":1.07,"rotation":95.78,"width":21,"height":37}},"left_leg_white":{"left_leg_white":{"x":13.52,"y":1.07,"rotation":95.78,"width":21,"height":37}},"right_hand":{"right_hand":{"x":14.45,"y":0.75,"rotation":3.24,"width":36,"height":21}},"right_hand_white":{"right_hand_white":{"x":14.45,"y":0.75,"rotation":3.24,"width":36,"height":21}},"right_leg":{"right_leg":{"x":13.33,"y":-0.58,"rotation":79.4,"width":20,"height":37}},"right_leg_white":{"right_leg_white":{"x":13.33,"y":-0.58,"rotation":79.4,"width":20,"height":37}},"shadow":{"shadow":{"x":4.67,"y":0.48,"rotation":89.65,"width":87,"height":14}},"shadow_white":{"shadow_white":{"x":4.67,"y":0.39,"rotation":90,"width":87,"height":14}}}}],"animations":{"Damage":{"slots":{"body_white":{"rgba":[{"time":0.0667,"color":"ffffffa7","curve":[0.2,1,0.067,1,0.2,1,0.067,1,0.2,1,0.067,1,0.2,0.66,0.067,0.49]},{"time":0.2,"color":"ffffff7b","curve":[0.3,1,0.2,1,0.3,1,0.2,1,0.3,1,0.2,1,0.3,0.49,0.2,0.26]},{"time":0.3,"color":"ffffff42","curve":[0.323,1,0.331,1,0.323,1,0.331,1,0.323,1,0.331,1,0.323,0.26,0.331,0.15]},{"time":0.3333,"color":"ffffff00","curve":[0.343,1,0.314,1,0.343,1,0.314,1,0.343,1,0.314,1,0.343,0,0.314,0]},{"time":0.4,"color":"ffffff00"}]},"head_white":{"rgba":[{"time":0.0667,"color":"ffffffa7","curve":[0.2,1,0.067,1,0.2,1,0.067,1,0.2,1,0.067,1,0.2,0.66,0.067,0.49]},{"time":0.2,"color":"ffffff7b","curve":[0.3,1,0.2,1,0.3,1,0.2,1,0.3,1,0.2,1,0.3,0.49,0.2,0.26]},{"time":0.3,"color":"ffffff42","curve":[0.323,1,0.331,1,0.323,1,0.331,1,0.323,1,0.331,1,0.323,0.26,0.331,0.15]},{"time":0.3333,"color":"ffffff00","curve":[0.343,1,0.314,1,0.343,1,0.314,1,0.343,1,0.314,1,0.343,0,0.314,0]},{"time":0.4,"color":"ffffff00"}]},"left_hand_right":{"rgba":[{"time":0.0667,"color":"ffffffa7","curve":[0.2,1,0.067,1,0.2,1,0.067,1,0.2,1,0.067,1,0.2,0.66,0.067,0.49]},{"time":0.2,"color":"ffffff7b","curve":[0.3,1,0.2,1,0.3,1,0.2,1,0.3,1,0.2,1,0.3,0.49,0.2,0.26]},{"time":0.3,"color":"ffffff42","curve":[0.323,1,0.331,1,0.323,1,0.331,1,0.323,1,0.331,1,0.323,0.26,0.331,0.15]},{"time":0.3333,"color":"ffffff00","curve":[0.343,1,0.314,1,0.343,1,0.314,1,0.343,1,0.314,1,0.343,0,0.314,0]},{"time":0.4,"color":"ffffff00"}]},"left_leg_white":{"rgba":[{"time":0.0667,"color":"ffffffa7","curve":[0.2,1,0.067,1,0.2,1,0.067,1,0.2,1,0.067,1,0.2,0.66,0.067,0.49]},{"time":0.2,"color":"ffffff7b","curve":[0.3,1,0.2,1,0.3,1,0.2,1,0.3,1,0.2,1,0.3,0.49,0.2,0.26]},{"time":0.3,"color":"ffffff42","curve":[0.323,1,0.331,1,0.323,1,0.331,1,0.323,1,0.331,1,0.323,0.26,0.331,0.15]},{"time":0.3333,"color":"ffffff00","curve":[0.343,1,0.314,1,0.343,1,0.314,1,0.343,1,0.314,1,0.343,0,0.314,0]},{"time":0.4,"color":"ffffff00"}]},"right_hand_white":{"rgba":[{"time":0.0667,"color":"ffffffa7","curve":[0.2,1,0.067,1,0.2,1,0.067,1,0.2,1,0.067,1,0.2,0.66,0.067,0.49]},{"time":0.2,"color":"ffffff7b","curve":[0.3,1,0.2,1,0.3,1,0.2,1,0.3,1,0.2,1,0.3,0.49,0.2,0.26]},{"time":0.3,"color":"ffffff42","curve":[0.323,1,0.331,1,0.323,1,0.331,1,0.323,1,0.331,1,0.323,0.26,0.331,0.15]},{"time":0.3333,"color":"ffffff00","curve":[0.343,1,0.314,1,0.343,1,0.314,1,0.343,1,0.314,1,0.343,0,0.314,0]},{"time":0.4,"color":"ffffff00"}]},"right_leg_white":{"rgba":[{"time":0.0667,"color":"ffffffa7","curve":[0.2,1,0.067,1,0.2,1,0.067,1,0.2,1,0.067,1,0.2,0.66,0.067,0.49]},{"time":0.2,"color":"ffffff7b","curve":[0.3,1,0.2,1,0.3,1,0.2,1,0.3,1,0.2,1,0.3,0.49,0.2,0.26]},{"time":0.3,"color":"ffffff42","curve":[0.323,1,0.331,1,0.323,1,0.331,1,0.323,1,0.331,1,0.323,0.26,0.331,0.15]},{"time":0.3333,"color":"ffffff00","curve":[0.343,1,0.314,1,0.343,1,0.314,1,0.343,1,0.314,1,0.343,0,0.314,0]},{"time":0.4,"color":"ffffff00"}]},"shadow_white":{"rgba":[{"time":0.0667,"color":"ffffffa7","curve":[0.2,1,0.067,1,0.2,1,0.067,1,0.2,1,0.067,1,0.2,0.66,0.067,0.49]},{"time":0.2,"color":"ffffff7b","curve":[0.3,1,0.2,1,0.3,1,0.2,1,0.3,1,0.2,1,0.3,0.49,0.2,0.26]},{"time":0.3,"color":"ffffff42","curve":[0.323,1,0.331,1,0.323,1,0.331,1,0.323,1,0.331,1,0.323,0.26,0.331,0.15]},{"time":0.3333,"color":"ffffff00","curve":[0.343,1,0.314,1,0.343,1,0.314,1,0.343,1,0.314,1,0.343,0,0.314,0]},{"time":0.4,"color":"ffffff00"}]}},"bones":{"right_leg":{"rotate":[{"value":-23.35}],"translate":[{"curve":[0.017,0,0.05,0,0.017,0,0.05,-2.23]},{"time":0.0667,"y":-2.23,"curve":[0.1,0,0.167,0,0.1,-2.23,0.167,-6.14]},{"time":0.2,"y":-6.14,"curve":[0.225,0,0.275,0,0.225,-6.14,0.275,-2.23]},{"time":0.3,"y":-2.23,"curve":[0.325,0,0.375,0,0.325,-2.23,0.375,-6.14]},{"time":0.4,"y":-6.14,"curve":[0.417,0,0.45,0,0.417,-6.14,0.45,0]},{"time":0.4667}],"scale":[{"curve":[0.017,1,0.05,1.156,0.017,1,0.05,1]},{"time":0.0667,"x":1.156,"curve":[0.1,1.156,0.167,0.892,0.1,1,0.167,1.034]},{"time":0.2,"x":0.892,"y":1.034,"curve":[0.225,0.892,0.275,1.156,0.225,1.034,0.275,1]},{"time":0.3,"x":1.156,"curve":[0.325,1.156,0.375,0.892,0.325,1,0.375,1.034]},{"time":0.4,"x":0.892,"y":1.034,"curve":[0.417,0.892,0.45,1,0.417,1.034,0.45,1]},{"time":0.4667}]},"left_leg":{"rotate":[{"value":20.57}],"translate":[{"curve":[0.017,0,0.05,0,0.017,0,0.05,-2.23]},{"time":0.0667,"y":-2.23,"curve":[0.1,0,0.167,0,0.1,-2.23,0.167,-6.14]},{"time":0.2,"y":-6.14,"curve":[0.225,0,0.275,0,0.225,-6.14,0.275,-2.23]},{"time":0.3,"y":-2.23,"curve":[0.325,0,0.375,0,0.325,-2.23,0.375,-6.14]},{"time":0.4,"y":-6.14,"curve":[0.417,0,0.45,0,0.417,-6.14,0.45,0]},{"time":0.4667}],"scale":[{"curve":[0.017,1,0.05,1.156,0.017,1,0.05,1]},{"time":0.0667,"x":1.156,"curve":[0.1,1.156,0.167,0.892,0.1,1,0.167,1.034]},{"time":0.2,"x":0.892,"y":1.034,"curve":[0.225,0.892,0.275,1.156,0.225,1.034,0.275,1]},{"time":0.3,"x":1.156,"curve":[0.325,1.156,0.375,0.892,0.325,1,0.375,1.034]},{"time":0.4,"x":0.892,"y":1.034,"curve":[0.417,0.892,0.45,1,0.417,1.034,0.45,1]},{"time":0.4667}]},"body":{"translate":[{"curve":[0.017,0,0.05,0,0.017,0,0.05,-2.23]},{"time":0.0667,"y":-2.23,"curve":[0.1,0,0.167,0,0.1,-2.23,0.167,-6.14]},{"time":0.2,"y":-6.14,"curve":[0.225,0,0.275,0,0.225,-6.14,0.275,-2.23]},{"time":0.3,"y":-2.23,"curve":[0.325,0,0.375,0,0.325,-2.23,0.375,-6.14]},{"time":0.4,"y":-6.14,"curve":[0.417,0,0.45,0,0.417,-6.14,0.45,0]},{"time":0.4667}],"scale":[{"curve":[0.017,1,0.05,1.156,0.017,1,0.05,1]},{"time":0.0667,"x":1.156,"curve":[0.1,1.156,0.167,0.892,0.1,1,0.167,1.034]},{"time":0.2,"x":0.892,"y":1.034,"curve":[0.225,0.892,0.275,1.156,0.225,1.034,0.275,1]},{"time":0.3,"x":1.156,"curve":[0.325,1.156,0.375,0.892,0.325,1,0.375,1.034]},{"time":0.4,"x":0.892,"y":1.034,"curve":[0.417,0.892,0.45,1,0.417,1.034,0.45,1]},{"time":0.4667}]},"head":{"scale":[{"curve":[0.017,1,0.05,1.156,0.017,1,0.05,1]},{"time":0.0667,"x":1.156,"curve":[0.1,1.156,0.167,0.892,0.1,1,0.167,1.034]},{"time":0.2,"x":0.892,"y":1.034,"curve":[0.225,0.892,0.275,1.156,0.225,1.034,0.275,1]},{"time":0.3,"x":1.156,"curve":[0.325,1.156,0.375,0.892,0.325,1,0.375,1.034]},{"time":0.4,"x":0.892,"y":1.034,"curve":[0.417,0.892,0.45,1,0.417,1.034,0.45,1]},{"time":0.4667}]},"left_hand":{"scale":[{"curve":[0.017,1,0.05,1.156,0.017,1,0.05,1]},{"time":0.0667,"x":1.156,"curve":[0.1,1.156,0.167,0.892,0.1,1,0.167,1.034]},{"time":0.2,"x":0.892,"y":1.034,"curve":[0.225,0.892,0.275,1.156,0.225,1.034,0.275,1]},{"time":0.3,"x":1.156,"curve":[0.325,1.156,0.375,0.892,0.325,1,0.375,1.034]},{"time":0.4,"x":0.892,"y":1.034,"curve":[0.417,0.892,0.45,1,0.417,1.034,0.45,1]},{"time":0.4667}]},"right_hand":{"scale":[{"curve":[0.017,1,0.05,1.156,0.017,1,0.05,1]},{"time":0.0667,"x":1.156,"curve":[0.1,1.156,0.167,0.892,0.1,1,0.167,1.034]},{"time":0.2,"x":0.892,"y":1.034,"curve":[0.225,0.892,0.275,1.156,0.225,1.034,0.275,1]},{"time":0.3,"x":1.156,"curve":[0.325,1.156,0.375,0.892,0.325,1,0.375,1.034]},{"time":0.4,"x":0.892,"y":1.034,"curve":[0.417,0.892,0.45,1,0.417,1.034,0.45,1]},{"time":0.4667}]},"shadow":{"translate":[{"curve":[0.017,0,0.05,0,0.017,0,0.05,-5.02]},{"time":0.0667,"y":-5.02,"curve":"stepped"},{"time":0.3,"y":-5.02,"curve":[0.342,0,0.425,0,0.342,-5.02,0.425,0]},{"time":0.4667}]}}},"Walk":{"slots":{"body_white":{"rgba":[{"color":"ffffff00"}]},"head_white":{"rgba":[{"color":"ffffff00"}]},"left_hand_right":{"rgba":[{"color":"ffffff00"}]},"left_leg_white":{"rgba":[{"color":"ffffff00"}]},"right_hand_white":{"rgba":[{"color":"ffffff00"}]},"right_leg_white":{"rgba":[{"color":"ffffff00"}]},"shadow_white":{"rgba":[{"color":"ffffff00"}]}},"bones":{"left_hand":{"rotate":[{"value":13.15,"curve":[0.037,15.79,0.071,17.35]},{"time":0.1,"value":17.35},{"time":0.7667,"value":-33.19,"curve":[0.905,-33.19,1.16,2.46]},{"time":1.3333,"value":13.15}]},"right_hand":{"rotate":[{"value":-11.26,"curve":[0.037,-13.35,0.071,-14.58]},{"time":0.1,"value":-14.58,"curve":[0.267,-14.58,0.6,25.33]},{"time":0.7667,"value":25.33,"curve":[0.905,25.33,1.16,-2.82]},{"time":1.3333,"value":-11.26}]},"right_leg":{"rotate":[{"value":-5.18},{"time":0.5,"value":-28.09},{"time":1.1667},{"time":1.3333,"value":-5.18}]},"left_leg":{"rotate":[{"value":4.24},{"time":0.5,"value":22.99},{"time":1.1667},{"time":1.3333,"value":4.24}]},"body":{"rotate":[{"value":3.31,"curve":[0.063,4.03,0.121,4.51]},{"time":0.1667,"value":4.51,"curve":[0.333,4.51,0.667,-2.01]},{"time":0.8333,"value":-2.01,"curve":[0.955,-2.01,1.167,1.54]},{"time":1.3333,"value":3.31}]}}}}}